{"pageProps":{"item":{"sys":{"space":{"sys":{"type":"Link","linkType":"Space","id":"9avvg8tgfdk2"}},"id":"3ns26vf2H650IHoRnghKNK","type":"Entry","createdAt":"2020-12-12T20:40:36.153Z","updatedAt":"2020-12-14T10:47:56.931Z","environment":{"sys":{"id":"master","type":"Link","linkType":"Environment"}},"revision":3,"contentType":{"sys":{"type":"Link","linkType":"ContentType","id":"bedRoomItem"}},"locale":"en-US"},"fields":{"productName":"Bedside tables","description":"The bedside tables put everything you need at your fingertips while lying in your bed. A glass of water, a novel for evening reading or an alarm clock. Keep them conveniently close to the bedside table.\n\nA small bedside table is the perfect choice if you just need a place for your cell phone. If you need enough space for a night light, candles, plants, or other decorative items, you may want to look at larger bedside tables with a larger surface area. Some bedside tables even have storage space on the lower shelf. The cabinet-style bedside table has small cabinets or drawers where you can keep accessories out of sight.\n\nWhether your style is traditional or modern, bold or minimalist - in the IKEA range you will find a bedside table that complements your bed .\n","productImage":{"sys":{"space":{"sys":{"type":"Link","linkType":"Space","id":"9avvg8tgfdk2"}},"id":"3nEptpoxvFWNq5WYn9XcMB","type":"Asset","createdAt":"2020-12-12T20:40:33.569Z","updatedAt":"2020-12-12T20:40:33.569Z","environment":{"sys":{"id":"master","type":"Link","linkType":"Environment"}},"revision":1,"locale":"en-US"},"fields":{"title":"Beside table","description":"Beside table image","file":{"url":"//images.ctfassets.net/9avvg8tgfdk2/3nEptpoxvFWNq5WYn9XcMB/86d3cb087bbbe0750d8231bb6fca5015/tables.webp","details":{"size":5572,"image":{"width":500,"height":281}},"fileName":"tables.webp","contentType":"image/webp"}}},"title":"The bedside table watches next to you","slug":"beside-tables","coverImage":{"sys":{"space":{"sys":{"type":"Link","linkType":"Space","id":"9avvg8tgfdk2"}},"id":"7BgmpsbIymJ9ktkRctGMdZ","type":"Asset","createdAt":"2020-12-14T10:47:48.505Z","updatedAt":"2020-12-14T10:47:48.505Z","environment":{"sys":{"id":"master","type":"Link","linkType":"Environment"}},"revision":1,"locale":"en-US"},"fields":{"title":"Beside tables","description":"Beside tables cover image","file":{"url":"//images.ctfassets.net/9avvg8tgfdk2/7BgmpsbIymJ9ktkRctGMdZ/59b34f1b0f8061de9d4c834c1d941241/beside-table.jpg","details":{"size":632802,"image":{"width":1920,"height":2879}},"fileName":"beside-table.jpg","contentType":"image/jpeg"}}}}}},"__N_SSG":true}